pedantic_timedelta/__init__.py
human_friendly_pedantic_timedelta-2.0.14.dist-info/LICENSE
human_friendly_pedantic_timedelta-2.0.14.dist-info/METADATA
human_friendly_pedantic_timedelta-2.0.14.dist-info/WHEEL
human_friendly_pedantic_timedelta-2.0.14.dist-info/RECORD
